frog_lib/__init__.py
frog_lib/frog_lib.py
frog_lib/omnigit.py
frog_lib/rest.py
frog_lib/utils.py
frog_lib-0.6.0.dist-info/WHEEL
frog_lib-0.6.0.dist-info/METADATA
frog_lib-0.6.0.dist-info/RECORD
