Metadata-Version: 2.1
Name: frog-lib
Version: 0.6.0
Summary: 
Author: Frog Dev
Author-email: dev@frog-mining.com
Requires-Python: >=3.7,<4.0
Classifier: Programming Language :: Python :: 3
Classifier: Programming Language :: Python :: 3.7
Classifier: Programming Language :: Python :: 3.8
Classifier: Programming Language :: Python :: 3.9
Requires-Dist: PyGithub (>=1.53,<2.0)
